{
  "meta": {
    "timestamp": "2022-11-03T07:41:43.543565Z",
    "stations_updated": "2022-09-05"
  },
  "altimeter": {
    "repr": "A3018",
    "value": 30.18,
    "spoken": "three zero point one eight"
  },
  "clouds": [
    {
      "repr": "SCT008",
      "type": "SCT",
      "altitude": 8,
      "modifier": null
    },
    {
      "repr": "SCT045",
      "type": "SCT",
      "altitude": 45,
      "modifier": null
    }
  ],
  "flight_rules": "VFR",
  "other": [],
  "visibility": {
    "repr": "10",
    "value": 10,
    "spoken": "one zero"
  },
  "wind_direction": null,
  "wind_gust": null,
  "wind_speed": null,
  "wx_codes": [],
  "raw": "KBVS 030735Z AUTO 10SM SCT008 SCT045 01/01 A3018 RMK A01",
  "sanitized": "KBVS 030735Z 10SM SCT008 SCT045 01/01 A3018 RMK A01",
  "station": "KBVS",
  "time": {
    "repr": "030735Z",
    "dt": "2022-11-03T07:35:00Z"
  },
  "remarks": "RMK A01",
  "dewpoint": {
    "repr": "01",
    "value": 1,
    "spoken": "one"
  },
  "relative_humidity": 1,
  "remarks_info": {
    "maximum_temperature_6": null,
    "minimum_temperature_6": null,
    "pressure_tendency": null,
    "precip_36_hours": null,
    "precip_24_hours": null,
    "sunshine_minutes": null,
    "codes": [],
    "dewpoint_decimal": null,
    "maximum_temperature_24": null,
    "minimum_temperature_24": null,
    "precip_hourly": null,
    "sea_level_pressure": null,
    "snow_depth": null,
    "temperature_decimal": null
  },
  "runway_visibility": [],
  "temperature": {
    "repr": "01",
    "value": 1,
    "spoken": "one"
  },
  "wind_variable_direction": [],
  "density_altitude": -1761,
  "pressure_altitude": -116,
  "units": {
    "accumulation": "in",
    "altimeter": "inHg",
    "altitude": "ft",
    "temperature": "C",
    "visibility": "sm",
    "wind_speed": "kt"
  }
}
