{
  "meta": {
    "timestamp": "2023-10-21T01:32:16.313517Z",
    "stations_updated": "2023-10-01"
  },
  "altimeter": {
    "repr": "A3000",
    "value": 30,
    "spoken": "three zero point zero zero"
  },
  "clouds": [
    {
      "repr": "BKN021",
      "type": "BKN",
      "altitude": 21,
      "modifier": null
    }
  ],
  "flight_rules": "MVFR",
  "other": [
    "11"
  ],
  "visibility": {
    "repr": "10",
    "value": 10,
    "spoken": "one zero"
  },
  "wind_direction": {
    "repr": "340",
    "value": 340,
    "spoken": "three four zero"
  },
  "wind_gust": null,
  "wind_speed": {
    "repr": "04",
    "value": 4,
    "spoken": "four"
  },
  "wx_codes": [],
  "raw": "KORS 210115Z AUTO 34004KT 10SM BKN021 11/ A3000 RMK AO2 KORS 210055Z AUTO 33005KT 10SM OVC020 12/ A3000 RMK AO2 KORS 210035Z AUTO 33005KT 10SM OVC018 12/ A3001 RMK AO2 KORS 210015Z AUTO 32007KT 9SM OVC016 12/ A3002 RMK AO2 KORS 202355Z AUTO 32005KT 10SM OVC012 12/ A3002 RMK AO2 KORS 202335Z AUTO 33006KT 10SM OVC012 12/ A3003 RMK AO2",
  "sanitized": "KORS 210115Z 34004KT 10SM BKN021 11 A3000 RMK AO2 KORS 210055Z AUTO 33005KT 10SM OVC020 12/ A3000 RMK AO2 KORS 210035Z AUTO 33005KT 10SM OVC018 12/ A3001 RMK AO2 KORS 210015Z AUTO 32007KT 9SM OVC016 12/ A3002 RMK AO2 KORS 202355Z AUTO 32005KT 10SM OVC012 12/ A3002 RMK AO2 KORS 202335Z AUTO 33006KT 10SM OVC012 12/ A3003 RMK AO2",
  "station": "KORS",
  "time": {
    "repr": "210115Z",
    "dt": "2023-10-21T01:15:00Z"
  },
  "remarks": "RMK AO2 KORS 210055Z AUTO 33005KT 10SM OVC020 12/ A3000 RMK AO2 KORS 210035Z AUTO 33005KT 10SM OVC018 12/ A3001 RMK AO2 KORS 210015Z AUTO 32007KT 9SM OVC016 12/ A3002 RMK AO2 KORS 202355Z AUTO 32005KT 10SM OVC012 12/ A3002 RMK AO2 KORS 202335Z AUTO 33006KT 10SM OVC012 12/ A3003 RMK AO2",
  "dewpoint": null,
  "relative_humidity": null,
  "remarks_info": {
    "maximum_temperature_6": null,
    "minimum_temperature_6": null,
    "pressure_tendency": null,
    "precip_36_hours": null,
    "precip_24_hours": null,
    "sunshine_minutes": null,
    "codes": [
      {
        "repr": "AO2",
        "value": "Automated with precipitation sensor"
      },
      {
        "repr": "AO2",
        "value": "Automated with precipitation sensor"
      },
      {
        "repr": "AO2",
        "value": "Automated with precipitation sensor"
      },
      {
        "repr": "AO2",
        "value": "Automated with precipitation sensor"
      },
      {
        "repr": "AO2",
        "value": "Automated with precipitation sensor"
      },
      {
        "repr": "AO2",
        "value": "Automated with precipitation sensor"
      }
    ],
    "dewpoint_decimal": null,
    "maximum_temperature_24": null,
    "minimum_temperature_24": null,
    "precip_hourly": null,
    "sea_level_pressure": null,
    "snow_depth": null,
    "temperature_decimal": null
  },
  "runway_visibility": [],
  "temperature": null,
  "wind_variable_direction": [],
  "density_altitude": null,
  "pressure_altitude": null,
  "units": {
    "accumulation": "in",
    "altimeter": "inHg",
    "altitude": "ft",
    "temperature": "C",
    "visibility": "sm",
    "wind_speed": "kt"
  }
}
